prob_phoc/_C.cpython-35m-x86_64-linux-gnu.so
prob_phoc/benchmark.py
prob_phoc/__init__.py
prob_phoc/test.py
prob_phoc/libcudart-f7fdd8d7.so.9.0
prob_phoc-0.2.0.dist-info/METADATA
prob_phoc-0.2.0.dist-info/WHEEL
prob_phoc-0.2.0.dist-info/LICENSE
prob_phoc-0.2.0.dist-info/top_level.txt
prob_phoc-0.2.0.dist-info/RECORD
